attack_executor/__init__.py
attack_executor/check_installation.py
attack_executor/cli.py
attack_executor/config.py
attack_executor/bash/CommandExecutor.py
attack_executor/bash/Shell.py
attack_executor/bash/__init__.py
attack_executor/doc/examples/nessus_example.py
attack_executor/exploit/Metasploit.py
attack_executor/exploit/test.py
attack_executor/exploit/test1.py
attack_executor/mcp/agent_openai.py
attack_executor/mcp/attack_executor_server.py
attack_executor/mcp/mcp_server.py
attack_executor/mcp/openai_demo.py
attack_executor/others/passwordGuesser.py
attack_executor/post_exploit/Sliver.py
attack_executor/priviledgeEscalation/Linpeas.py
attack_executor/priviledgeEscalation/test_real_linpeas.py
attack_executor/scan/__init__.py
attack_executor/scan/gobuster.py
attack_executor/scan/nessus.py
attack_executor/scan/nessus_parser.py
attack_executor/scan/nessus_scanning.py
attack_executor/scan/nmap.py
attack_executor/scan/nuclei.py
attack_executor/scan/whatweb.py
attack_executor/search/exploitdb.py
attack_executor/search/searchsploit.py
attack_executor-0.2.7.dist-info/licenses/LICENSE
attack_executor-0.2.7.dist-info/METADATA
attack_executor-0.2.7.dist-info/WHEEL
attack_executor-0.2.7.dist-info/entry_points.txt
attack_executor-0.2.7.dist-info/top_level.txt
attack_executor-0.2.7.dist-info/RECORD
