Metadata-Version: 2.4
Name: attack_executor
Version: 0.2.7
Summary: This library provides standard Python APIs to interact with common penetration testing and cyberattack tools, enabling automated penetration testing, red team operations, and development of cybersecurity-related LLM agents.
Author-email: Lexus Wang <lingzhiwang2025@u.northwestern.edu>
License: MIT
Requires-Python: >=3.11
License-File: LICENSE
Requires-Dist: sliver-py>=0.0.19
Requires-Dist: pymetasploit3>=1.0.6
Requires-Dist: rich>=14.0.0
Dynamic: license-file
